earnorm/README.md
earnorm/__init__.py
earnorm/api.py
earnorm/base/README.md
earnorm/base/__init__.py
earnorm/base/database/README.md
earnorm/base/database/__init__.py
earnorm/base/database/adapter.py
earnorm/base/database/adapters/README.md
earnorm/base/database/adapters/__init__.py
earnorm/base/database/adapters/mongo.py
earnorm/base/database/query/README.md
earnorm/base/database/query/__init__.py
earnorm/base/database/query/backends/README.md
earnorm/base/database/query/backends/__init__.py
earnorm/base/database/query/backends/mongo/README.md
earnorm/base/database/query/backends/mongo/__init__.py
earnorm/base/database/query/backends/mongo/builder.py
earnorm/base/database/query/backends/mongo/converter.py
earnorm/base/database/query/backends/mongo/operations/README.md
earnorm/base/database/query/backends/mongo/operations/__init__.py
earnorm/base/database/query/backends/mongo/operations/aggregate.py
earnorm/base/database/query/backends/mongo/operations/join.py
earnorm/base/database/query/backends/mongo/operations/window.py
earnorm/base/database/query/backends/mongo/query.py
earnorm/base/database/query/core/README.md
earnorm/base/database/query/core/operations/README.md
earnorm/base/database/query/core/operations/__init__.py
earnorm/base/database/query/core/operations/aggregate.py
earnorm/base/database/query/core/operations/base.py
earnorm/base/database/query/core/operations/join.py
earnorm/base/database/query/core/operations/window.py
earnorm/base/database/query/core/query.py
earnorm/base/database/query/interfaces/README.md
earnorm/base/database/query/interfaces/__init__.py
earnorm/base/database/query/interfaces/domain.py
earnorm/base/database/query/interfaces/field.py
earnorm/base/database/query/interfaces/operations/README.md
earnorm/base/database/query/interfaces/operations/__init__.py
earnorm/base/database/query/interfaces/operations/aggregate.py
earnorm/base/database/query/interfaces/operations/base.py
earnorm/base/database/query/interfaces/operations/join.py
earnorm-0.1.1.dist-info/LICENSE
earnorm-0.1.1.dist-info/METADATA
earnorm-0.1.1.dist-info/WHEEL
earnorm-0.1.1.dist-info/entry_points.txt
earnorm-0.1.1.dist-info/RECORD
