Metadata-Version: 2.3
Name: earnorm
Version: 0.1.1
Summary: EarnBase ORM - Async-first ORM for MongoDB and more
Keywords: orm,mongodb,async,database,earnbase
Author: EarnBase
Author-email: dev@earnbase.com
Requires-Python: >=3.12,<4.0
Classifier: Development Status :: 4 - Beta
Classifier: Framework :: AsyncIO
Classifier: Intended Audience :: Developers
Classifier: License :: OSI Approved :: MIT License
Classifier: Programming Language :: Python :: 3
Classifier: Programming Language :: Python :: 3.12
Classifier: Programming Language :: Python :: 3.13
Classifier: Topic :: Database
Classifier: Topic :: Software Development :: Libraries :: Python Modules
Requires-Dist: PyYAML (>=6.0.2,<7.0.0)
Requires-Dist: aiomysql (>=0.2.0,<0.3.0)
Requires-Dist: asyncpg (>=0.30.0,<0.31.0)
Requires-Dist: dependency-injector (>=4.45.0,<5.0.0)
Requires-Dist: fastapi (>=0.115.6,<0.116.0)
Requires-Dist: jsonschema (>=4.23.0,<5.0.0)
Requires-Dist: motor (>=3.6.1,<4.0.0)
Requires-Dist: phonenumbers (>=8.13.52,<9.0.0)
Requires-Dist: prometheus-client (>=0.21.1,<0.22.0)
Requires-Dist: psutil (>=6.1.1,<7.0.0)
Requires-Dist: pydantic (>=2.6.1,<3.0.0)
Requires-Dist: pymongo (==4.9.2)
Requires-Dist: python-dotenv (>=1.0.1,<2.0.0)
Requires-Dist: redis (>=5.2.1,<6.0.0)
Requires-Dist: rich (>=13.9.4,<14.0.0)
Requires-Dist: structlog (>=24.4.0,<25.0.0)
Requires-Dist: typing-extensions (>=4.12.2,<5.0.0)
Project-URL: Documentation, https://earnorm.readthedocs.io
Project-URL: Homepage, https://github.com/earnbase/earnorm
Project-URL: Repository, https://github.com/earnbase/earnorm
